datasculpt/__init__.py
datasculpt/cli.py
datasculpt/compatibility.py
datasculpt/decision.py
datasculpt/intake.py
datasculpt/interactive.py
datasculpt/pipeline.py
datasculpt/proposal.py
datasculpt/py.typed
datasculpt/query.py
datasculpt/registration.py
datasculpt/adapters/__init__.py
datasculpt/adapters/base.py
datasculpt/adapters/dataprofiler.py
datasculpt/adapters/frictionless.py
datasculpt/adapters/reporting.py
datasculpt/core/__init__.py
datasculpt/core/evidence.py
datasculpt/core/grain.py
datasculpt/core/roles.py
datasculpt/core/shapes.py
datasculpt/core/special.py
datasculpt/core/time.py
datasculpt/core/types.py
datasculpt-0.1.0.dist-info/METADATA
datasculpt-0.1.0.dist-info/WHEEL
datasculpt-0.1.0.dist-info/entry_points.txt
datasculpt-0.1.0.dist-info/RECORD
