Metadata-Version: 2.4
Name: datasculpt
Version: 0.1.0
Summary: Deterministic dataset shape and semantic inference for Invariant
Project-URL: Repository, https://github.com/adieyal/datasculpt
Project-URL: Documentation, https://adieyal.github.io/datasculpt/
Author-email: Adi Eyal <adi@clearforest.io>
License: MIT
Keywords: data,inference,profiling,schema,tabular
Classifier: Development Status :: 3 - Alpha
Classifier: Intended Audience :: Developers
Classifier: License :: OSI Approved :: MIT License
Classifier: Programming Language :: Python :: 3
Classifier: Programming Language :: Python :: 3.11
Classifier: Programming Language :: Python :: 3.12
Classifier: Programming Language :: Python :: 3.13
Classifier: Topic :: Scientific/Engineering :: Information Analysis
Classifier: Typing :: Typed
Requires-Python: >=3.11
Requires-Dist: pandas>=2.0
Provides-Extra: all
Requires-Dist: dataprofiler>=0.12; extra == 'all'
Requires-Dist: frictionless>=5.0; extra == 'all'
Requires-Dist: ydata-profiling>=4.0; extra == 'all'
Provides-Extra: dataprofiler
Requires-Dist: dataprofiler>=0.12; extra == 'dataprofiler'
Provides-Extra: dev
Requires-Dist: mypy>=1.10; extra == 'dev'
Requires-Dist: pandas-stubs>=2.0; extra == 'dev'
Requires-Dist: pytest-cov>=4.0; extra == 'dev'
Requires-Dist: pytest>=8.0; extra == 'dev'
Requires-Dist: ruff>=0.4; extra == 'dev'
Provides-Extra: docs
Requires-Dist: mkdocs-material>=9.0; extra == 'docs'
Requires-Dist: mkdocs>=1.5; extra == 'docs'
Provides-Extra: frictionless
Requires-Dist: frictionless>=5.0; extra == 'frictionless'
Provides-Extra: reporting
Requires-Dist: ydata-profiling>=4.0; extra == 'reporting'
